astprettier.py
astprettier-0.1.dist-info/METADATA
astprettier-0.1.dist-info/WHEEL
astprettier-0.1.dist-info/entry_points.txt
astprettier-0.1.dist-info/top_level.txt
astprettier-0.1.dist-info/RECORD
