Metadata-Version: 2.1
Name: astprettier
Version: 0.1
Summary: Pretty print the output of python stdlib `ast.parse`.
License: Copyright (c)      2022 Ronny Rentner
Project-URL: main, https://github.com/ronny-rentner/astprettier
Classifier: License :: OSI Approved :: MIT License
Classifier: Programming Language :: Python :: 3
Classifier: Programming Language :: Python :: 3 :: Only
Classifier: Programming Language :: Python :: 3.8
Classifier: Programming Language :: Python :: 3.9
Classifier: Programming Language :: Python :: 3.10
Requires-Python: >=3.8
Provides-Extra: colorize
Requires-Dist: pygments ; extra == 'colorize'
Provides-Extra: test
Requires-Dist: ultraimport ; extra == 'test'
Requires-Dist: pytest ; extra == 'test'
